CHANGELOG.txt
LICENCE.txt
MANIFEST.in
README.txt
setup.py
main/__init__.py
pycell.egg-info/PKG-INFO
pycell.egg-info/SOURCES.txt
pycell.egg-info/dependency_links.txt
pycell.egg-info/top_level.txt